{
  "$schema": "https://biomejs.dev/schemas/2.5.1/schema.json",
  "formatter": {
    "enabled": true,
    "formatWithErrors": false,
    "includes": [
      "**",
      "!**/package.json",
      "!**/pnpm-lock.yaml",
      "!**/next-env.d.ts",
      "!**/.next/**",
      "!**/out/**",
      "!**/dist/**",
      "!**/build/**",
      "!**/lib/**",
      "!**/app/global.css"
    ],
    "indentStyle": "space",
    "indentWidth": 2,
    "lineEnding": "lf",
    "lineWidth": 80,
    "attributePosition": "auto"
  },
  "assist": { "actions": { "source": { "organizeImports": "on" } } },
  "linter": { "enabled": true, "rules": { "preset": "recommended" } },
  "javascript": {
    "formatter": {
      "jsxQuoteStyle": "double",
      "quoteProperties": "asNeeded",
      "trailingCommas": "none",
      "semicolons": "asNeeded",
      "arrowParentheses": "asNeeded",
      "bracketSpacing": true,
      "bracketSameLine": false,
      "quoteStyle": "single",
      "attributePosition": "auto"
    }
  },
  "files": {
    "includes": [
      "**",
      "!**/package.json",
      "!**/pnpm-lock.yaml",
      "!**/next-env.d.ts",
      "!**/.next/**",
      "!**/out/**",
      "!**/dist/**",
      "!**/build/**",
      "!**/lib/**",
      "!**/app/global.css"
    ]
  }
}
